{"name":"SV Voorburg Rapid","number_of_rounds":7,"players":[{"federation":"MRI","flags":"","gender":"M","id":"97845632","name":"John Wick","official_rating":true,"pairing_number":1,"rating":1587},{"federation":"NED","flags":"","gender":"F","id":"9874663","name":"Rose Park","official_rating":true,"pairing_number":2,"rating":1254},{"federation":"NED","flags":"","gender":"M","id":"","name":"Tom West","official_rating":true,"pairing_number":3,"rating":1154},{"federation":"NED","flags":"","gender":"M","id":"","name":"Roberto Signal","official_rating":true,"pairing_number":4,"rating":1765},{"federation":"NED","flags":"","gender":"M","id":"874563","name":"John Black","official_rating":true,"pairing_number":5,"rating":0},{"federation":"","flags":"","gender":"F","id":"","name":"Laura San","official_rating":true,"pairing_number":6,"rating":1954}],"rounds":[{"byes":[],"date":"2025-10-23","number":1,"pairings":[{"black":1,"black_points":0.0,"table":1,"white":4,"white_points":1.0},{"black":5,"black_points":0.5,"table":2,"white":2,"white_points":0.5},{"black":3,"black_points":0.5,"table":3,"white":6,"white_points":0.5}],"ranking":[{"average_rating_cut":1587.0,"buchholz":0.0,"buchholz_cut":0.0,"color_balance":1,"mutual_result_top":0.0,"player":4,"progressive_score":1.0,"rank":1,"score":1.0,"sonneborn_berger":0.0,"tpr":2387,"tpr_mixed":2387,"w_we":0.27},{"average_rating_cut":1154.0,"buchholz":0.5,"buchholz_cut":0.5,"color_balance":1,"player":6,"progressive_score":0.5,"rank":2,"score":0.5,"sonneborn_berger":0.25,"tpr":1554,"tpr_mixed":1154,"w_we":-0.42},{"average_rating_cut":1000.0,"buchholz":0.5,"buchholz_cut":0.5,"color_balance":1,"player":2,"progressive_score":0.5,"rank":3,"score":0.5,"sonneborn_berger":0.25,"tpr":0,"tpr_mixed":0,"w_we":0.0},{"average_rating_cut":1954.0,"buchholz":0.5,"buchholz_cut":0.5,"color_balance":-1,"player":3,"progressive_score":0.5,"rank":4,"score":0.5,"sonneborn_berger":0.25,"tpr":1554,"tpr_mixed":1954,"w_we":0.42},{"average_rating_cut":1254.0,"buchholz":0.5,"buchholz_cut":0.5,"color_balance":-1,"player":5,"progressive_score":0.5,"rank":5,"score":0.5,"sonneborn_berger":0.25,"tpr":1254,"tpr_mixed":1254},{"average_rating_cut":1765.0,"buchholz":1.0,"buchholz_cut":1.0,"color_balance":-1,"player":1,"progressive_score":0.0,"rank":6,"score":0.0,"sonneborn_berger":0.0,"tpr":965,"tpr_mixed":965,"w_we":-0.27}]},{"byes":[],"date":"2025-10-23","number":2,"pairings":[{"black":4,"black_points":1.0,"table":1,"white":3,"white_points":0.0},{"black":6,"black_points":1.0,"table":2,"white":5,"white_points":0.0},{"black":2,"black_points":0.0,"table":3,"white":1,"white_points":1.0}],"ranking":[{"average_rating_cut":1370.5,"buchholz":1.5,"buchholz_cut":1.5,"color_balance":0,"mutual_result_top":0.0,"player":4,"progressive_score":3.0,"rank":1,"score":2.0,"sonneborn_berger":1.5,"tpr":2276,"tpr_mixed":2171,"w_we":0.35000000000000003},{"average_rating_cut":1077.0,"buchholz":1.0,"buchholz_cut":1.0,"color_balance":0,"player":6,"progressive_score":2.0,"rank":2,"score":1.5,"sonneborn_berger":0.75,"tpr":1554,"tpr_mixed":1154,"w_we":-0.42},{"average_rating_cut":1509.5,"buchholz":2.5,"buchholz_cut":2.5,"color_balance":0,"player":1,"progressive_score":1.0,"rank":3,"score":1.0,"sonneborn_berger":0.5,"tpr":1510,"tpr_mixed":1510,"w_we":-0.15},{"average_rating_cut":1293.5,"buchholz":1.5,"buchholz_cut":1.5,"color_balance":0,"player":2,"progressive_score":1.0,"rank":4,"score":0.5,"sonneborn_berger":0.25,"tpr":787,"tpr_mixed":787,"w_we":-0.12},{"average_rating_cut":1859.5,"buchholz":3.5,"buchholz_cut":3.5,"color_balance":0,"player":3,"progressive_score":1.0,"rank":5,"score":0.5,"sonneborn_berger":0.75,"tpr":1361,"tpr_mixed":1667,"w_we":0.34},{"average_rating_cut":1604.0,"buchholz":2.0,"buchholz_cut":2.0,"color_balance":0,"player":5,"progressive_score":1.0,"rank":6,"score":0.5,"sonneborn_berger":0.25,"tpr":1411,"tpr_mixed":1411}]},{"byes":[],"date":"2025-10-23","number":3,"pairings":[{"black":6,"black_points":0.5,"table":1,"white":4,"white_points":0.5},{"black":1,"black_points":0.0,"table":2,"white":5,"white_points":1.0},{"black":3,"black_points":0.0,"table":3,"white":2,"white_points":1.0}],"ranking":[{"average_rating_cut":1770.5,"buchholz":3.5,"buchholz_cut":3.0,"color_balance":1,"mutual_result_top":0.0,"player":4,"progressive_score":5.5,"rank":1,"score":2.5,"sonneborn_berger":2.5,"tpr":1908,"tpr_mixed":1838,"w_we":0.6},{"average_rating_cut":1459.5,"buchholz":4.5,"buchholz_cut":4.0,"color_balance":-1,"player":6,"progressive_score":4.0,"rank":2,"score":2.0,"sonneborn_berger":3.0,"tpr":1660,"tpr_mixed":1460,"w_we":-0.67},{"average_rating_cut":1370.5,"buchholz":3.0,"buchholz_cut":2.5,"color_balance":1,"player":2,"progressive_score":2.5,"rank":3,"score":1.5,"sonneborn_berger":1.25,"tpr":1371,"tpr_mixed":1371,"w_we":0.24},{"average_rating_cut":1770.5,"buchholz":4.5,"buchholz_cut":3.5,"color_balance":1,"player":5,"progressive_score":2.5,"rank":4,"score":1.5,"sonneborn_berger":1.75,"tpr":1598,"tpr_mixed":1598},{"average_rating_cut":1509.5,"buchholz":5.5,"buchholz_cut":4.0,"color_balance":-1,"player":1,"progressive_score":2.0,"rank":5,"score":1.0,"sonneborn_berger":1.5,"tpr":1510,"tpr_mixed":1510,"w_we":-0.15},{"average_rating_cut":1859.5,"buchholz":6.0,"buchholz_cut":4.5,"color_balance":-1,"player":3,"progressive_score":1.5,"rank":6,"score":0.5,"sonneborn_berger":1.0,"tpr":1181,"tpr_mixed":1385,"w_we":-0.02}]},{"byes":[],"date":"2025-10-23","number":4,"pairings":[{"black":5,"black_points":0.5,"table":1,"white":4,"white_points":0.5},{"black":2,"black_points":0.5,"table":2,"white":6,"white_points":0.5},{"black":3,"black_points":0.0,"table":3,"white":1,"white_points":1.0}],"ranking":[{"average_rating_cut":1370.5,"buchholz":7.0,"buchholz_cut":4.0,"color_balance":2,"mutual_result_top":0.0,"player":4,"progressive_score":8.5,"rank":1,"score":3.0,"sonneborn_berger":4.75,"tpr":1908,"tpr_mixed":1838,"w_we":0.6},{"average_rating_cut":1204.0,"buchholz":7.5,"buchholz_cut":4.0,"color_balance":0,"player":6,"progressive_score":6.5,"rank":2,"score":2.5,"sonneborn_berger":4.75,"tpr":1624,"tpr_mixed":1391,"w_we":-1.09},{"average_rating_cut":1204.0,"buchholz":7.5,"buchholz_cut":4.0,"color_balance":0,"player":1,"progressive_score":4.0,"rank":3,"score":2.0,"sonneborn_berger":2.5,"tpr":1527,"tpr_mixed":1516,"w_we":-0.07},{"average_rating_cut":1370.5,"buchholz":7.0,"buchholz_cut":4.0,"color_balance":0,"player":2,"progressive_score":4.5,"rank":4,"score":2.0,"sonneborn_berger":2.75,"tpr":1465,"tpr_mixed":1565,"w_we":0.66},{"average_rating_cut":1676.0,"buchholz":9.5,"buchholz_cut":4.5,"color_balance":0,"player":5,"progressive_score":4.5,"rank":5,"score":2.0,"sonneborn_berger":4.5,"tpr":1640,"tpr_mixed":1640},{"average_rating_cut":1676.0,"buchholz":9.5,"buchholz_cut":4.5,"color_balance":-2,"player":3,"progressive_score":2.0,"rank":6,"score":0.5,"sonneborn_berger":1.25,"tpr":1157,"tpr_mixed":1318,"w_we":-0.1}]},{"byes":[],"date":"2025-10-23","number":5,"pairings":[{"black":4,"black_points":0.0,"table":1,"white":2,"white_points":1.0},{"black":1,"black_points":1.0,"table":2,"white":6,"white_points":0.0},{"black":5,"black_points":1.0,"table":3,"white":3,"white_points":0.0}],"ranking":[{"average_rating_cut":1331.7,"buchholz":12.0,"buchholz_cut":8.5,"color_balance":1,"mutual_result_top":1.5,"player":4,"progressive_score":11.5,"rank":1,"score":3.0,"sonneborn_berger":6.25,"tpr":1663,"tpr_mixed":1582,"w_we":-0.32},{"average_rating_cut":1391.0,"buchholz":12.0,"buchholz_cut":8.5,"color_balance":-1,"mutual_result_top":1.0,"player":1,"progressive_score":7.0,"rank":2,"score":3.0,"sonneborn_berger":6.0,"tpr":1733,"tpr_mixed":1725,"w_we":0.8300000000000001},{"average_rating_cut":1502.0,"buchholz":12.0,"buchholz_cut":8.5,"color_balance":1,"mutual_result_top":1.5,"player":2,"progressive_score":7.5,"rank":3,"score":3.0,"sonneborn_berger":6.25,"tpr":1607,"tpr_mixed":1710,"w_we":1.58},{"average_rating_cut":1535.3000000000002,"buchholz":12.0,"buchholz_cut":8.5,"color_balance":-1,"mutual_result_top":2.0,"player":5,"progressive_score":7.5,"rank":4,"score":3.0,"sonneborn_berger":6.5,"tpr":1615,"tpr_mixed":1615,"w_we":0.5},{"average_rating_cut":1331.7,"buchholz":12.5,"buchholz_cut":9.0,"color_balance":1,"player":6,"progressive_score":9.0,"rank":5,"score":2.5,"sonneborn_berger":6.25,"tpr":1528,"tpr_mixed":1353,"w_we":-1.99},{"average_rating_cut":1535.3000000000002,"buchholz":14.5,"buchholz_cut":9.0,"color_balance":-1,"player":3,"progressive_score":2.5,"rank":6,"score":0.5,"sonneborn_berger":1.25,"tpr":1157,"tpr_mixed":1318,"w_we":-0.1}]},{"byes":[{"player":1,"score":1.0},{"player":2,"score":1.0},{"player":3,"score":1.0},{"player":4,"score":1.0},{"player":5,"score":1.0},{"player":6,"score":1.0}],"date":"2025-10-23","number":6,"pairings":[],"ranking":[{"average_rating_cut":1248.8000000000002,"buchholz":17.5,"buchholz_cut":13.0,"color_balance":2,"mutual_result_top":1.5,"player":4,"progressive_score":15.5,"rank":1,"score":4.0,"sonneborn_berger":10.75,"tpr":1663,"tpr_mixed":1582,"w_we":-0.32},{"average_rating_cut":1293.3000000000002,"buchholz":17.5,"buchholz_cut":13.0,"color_balance":0,"mutual_result_top":1.0,"player":1,"progressive_score":11.0,"rank":2,"score":4.0,"sonneborn_berger":10.5,"tpr":1733,"tpr_mixed":1725,"w_we":0.8300000000000001},{"average_rating_cut":1376.5,"buchholz":17.5,"buchholz_cut":13.0,"color_balance":2,"mutual_result_top":1.5,"player":2,"progressive_score":11.5,"rank":3,"score":4.0,"sonneborn_berger":10.75,"tpr":1607,"tpr_mixed":1710,"w_we":1.58},{"average_rating_cut":1440.0,"buchholz":17.5,"buchholz_cut":13.0,"color_balance":0,"mutual_result_top":2.0,"player":5,"progressive_score":11.5,"rank":4,"score":4.0,"sonneborn_berger":11.0,"tpr":1615,"tpr_mixed":1615,"w_we":0.5},{"average_rating_cut":1248.8000000000002,"buchholz":17.5,"buchholz_cut":13.0,"color_balance":2,"player":6,"progressive_score":12.5,"rank":5,"score":3.5,"sonneborn_berger":10.0,"tpr":1528,"tpr_mixed":1353,"w_we":-1.99},{"average_rating_cut":1401.5,"buchholz":17.5,"buchholz_cut":13.5,"color_balance":0,"player":3,"progressive_score":4.0,"rank":6,"score":1.5,"sonneborn_berger":2.0,"tpr":1157,"tpr_mixed":1318,"w_we":-0.1}]},{"byes":[{"player":1,"score":1.0},{"player":2,"score":1.0},{"player":3,"score":1.0},{"player":4,"score":1.0},{"player":5,"score":1.0},{"player":6,"score":1.0}],"date":"2025-10-23","number":7,"pairings":[],"ranking":[{"average_rating_cut":1248.8000000000002,"buchholz":24.5,"buchholz_cut":19.0,"color_balance":3,"mutual_result_top":1.5,"player":4,"progressive_score":20.5,"rank":1,"score":5.0,"sonneborn_berger":16.75,"tpr":1663,"tpr_mixed":1582,"w_we":-0.32},{"average_rating_cut":1293.3000000000002,"buchholz":24.5,"buchholz_cut":19.0,"color_balance":1,"mutual_result_top":1.0,"player":1,"progressive_score":16.0,"rank":2,"score":5.0,"sonneborn_berger":16.5,"tpr":1733,"tpr_mixed":1725,"w_we":0.8300000000000001},{"average_rating_cut":1376.5,"buchholz":24.5,"buchholz_cut":19.0,"color_balance":3,"mutual_result_top":1.5,"player":2,"progressive_score":16.5,"rank":3,"score":5.0,"sonneborn_berger":16.75,"tpr":1607,"tpr_mixed":1710,"w_we":1.58},{"average_rating_cut":1440.0,"buchholz":24.5,"buchholz_cut":19.0,"color_balance":1,"mutual_result_top":2.0,"player":5,"progressive_score":16.5,"rank":4,"score":5.0,"sonneborn_berger":17.0,"tpr":1615,"tpr_mixed":1615,"w_we":0.5},{"average_rating_cut":1248.8000000000002,"buchholz":24.0,"buchholz_cut":18.5,"color_balance":3,"player":6,"progressive_score":17.0,"rank":5,"score":4.5,"sonneborn_berger":15.25,"tpr":1528,"tpr_mixed":1353,"w_we":-1.99},{"average_rating_cut":1401.5,"buchholz":22.0,"buchholz_cut":17.0,"color_balance":1,"player":3,"progressive_score":6.5,"rank":6,"score":2.5,"sonneborn_berger":4.25,"tpr":1157,"tpr_mixed":1318,"w_we":-0.1}]}],"tiebreaks":["score","rating"],"updated_at":"2025-11-12T19:19:22Z"}